{
  "description": "GetCmdDf",

  "cases": [

    {
      "kernel": "",
      "os": "",
      "cpu": "x86",
      "lepdResult":	"Filesystem                Size      Used Available Use% Mounted on\nudev                    479.4M      4.0K    479.4M   0% /dev\ntmpfs                    97.9M    800.0K     97.1M   1% /run\n/dev/disk/by-uuid/94630df9-14e5-4af3-bb7e-47b4a88b5c6f\n                         18.6G      4.4G     13.2G  25% /\ncgroup                  489.6M         0    489.6M   0% /sys/fs/cgroup\nnone                      5.0M      4.0K      5.0M   0% /run/lock\nnone                    489.6M    152.0K    489.5M   0% /run/shm\n/dev/disk/by-uuid/94630df9-14e5-4af3-bb7e-47b4a88b5c6f\n                         18.6G      4.4G     13.2G  25% /var/lib/docker/aufs\nlepdendstring",
      "expected": {
        "data": {
          "disks": {
            "/dev": {
              "mountPoint": "/dev",
              "Use%": 0,
              "Available": 479.4,
              "Available.unit": "M",
              "Used": 4,
              "Used.unit": "K",
              "Size": 479.4,
              "Size.unit": "M",
              "Filesystem": "udev"
            },
            "/run": {
              "mountPoint": "/run",
              "Use%": 1,
              "Available": 97.1,
              "Available.unit": "M",
              "Used": 800,
              "Used.unit": "K",
              "Size": 97.9,
              "Size.unit": "M",
              "Filesystem": "tmpfs"
            },
            "/": {
              "mountPoint": "/",
              "Use%": 25,
              "Available": 13.2,
              "Available.unit": "G",
              "Used": 4.4,
              "Used.unit": "G",
              "Size": 18.6,
              "Size.unit": "G"
            },
            "/sys/fs/cgroup": {
              "mountPoint": "/sys/fs/cgroup",
              "Use%": 0,
              "Available": 489.6,
              "Available.unit": "M",
              "Used": 0,
              "Used.unit": "",
              "Size": 489.6,
              "Size.unit": "M",
              "Filesystem": "cgroup"
            },
            "/run/lock": {
              "mountPoint": "/run/lock",
              "Use%": 0,
              "Available": 5,
              "Available.unit": "M",
              "Used": 4,
              "Used.unit": "K",
              "Size": 5,
              "Size.unit": "M",
              "Filesystem": "none"
            },
            "/run/shm": {
              "mountPoint": "/run/shm",
              "Use%": 0,
              "Available": 489.5,
              "Available.unit": "M",
              "Used": 152,
              "Used.unit": "K",
              "Size": 489.6,
              "Size.unit": "M",
              "Filesystem": "none"
            },
            "/var/lib/docker/aufs": {
              "mountPoint": "/var/lib/docker/aufs",
              "Use%": 25,
              "Available": 13.2,
              "Available.unit": "G",
              "Used": 4.4,
              "Used.unit": "G",
              "Size": 18.6,
              "Size.unit": "G"
            }
          }
        }
      }
    },

    {
      "kernel": "",
      "os": "",
      "cpu": "arm",
      "lepdResult":	"Filesystem                Size      Used Available Use% Mounted on\nnone                    437.2M      4.0K    437.2M   0% /dev\n/dev/nandd                3.6G      1.4G      1.9G  42% /\nnone                    437.2M      4.0K    437.2M   0% /dev\nnone                    438.0M      4.0K    438.0M   0% /tmp\nnone                     87.6M    200.0K     87.4M   0% /run\nnone                      5.0M         0      5.0M   0% /run/lock\nnone                    438.0M         0    438.0M   0% /run/shm\nnone                    438.0M         0    438.0M   0% /var/tmp\nnone                    438.0M    572.0K    437.4M   0% /var/log\nlepdendstring",
      "expected": {
        "data": {
          "disks": {
            "/dev": {
              "mountPoint": "/dev",
              "Use%": 0,
              "Available": 437.2,
              "Available.unit": "M",
              "Used": 4,
              "Used.unit": "K",
              "Size": 437.2,
              "Size.unit": "M",
              "Filesystem": "none"
            },
            "/": {
              "mountPoint": "/",
              "Use%": 42,
              "Available": 1.9,
              "Available.unit": "G",
              "Used": 1.4,
              "Used.unit": "G",
              "Size": 3.6,
              "Size.unit": "G",
              "Filesystem": "/dev/nandd"
            },
            "/tmp": {
              "mountPoint": "/tmp",
              "Use%": 0,
              "Available": 438,
              "Available.unit": "M",
              "Used": 4,
              "Used.unit": "K",
              "Size": 438,
              "Size.unit": "M",
              "Filesystem": "none"
            },
            "/run": {
              "mountPoint": "/run",
              "Use%": 0,
              "Available": 87.4,
              "Available.unit": "M",
              "Used": 200,
              "Used.unit": "K",
              "Size": 87.6,
              "Size.unit": "M",
              "Filesystem": "none"
            },
            "/run/lock": {
              "mountPoint": "/run/lock",
              "Use%": 0,
              "Available": 5,
              "Available.unit": "M",
              "Used": 0,
              "Used.unit": "",
              "Size": 5,
              "Size.unit": "M",
              "Filesystem": "none"
            },
            "/run/shm": {
              "mountPoint": "/run/shm",
              "Use%": 0,
              "Available": 438,
              "Available.unit": "M",
              "Used": 0,
              "Used.unit": "",
              "Size": 438,
              "Size.unit": "M",
              "Filesystem": "none"
            },
            "/var/tmp": {
              "mountPoint": "/var/tmp",
              "Use%": 0,
              "Available": 438,
              "Available.unit": "M",
              "Used": 0,
              "Used.unit": "",
              "Size": 438,
              "Size.unit": "M",
              "Filesystem": "none"
            },
            "/var/log": {
              "mountPoint": "/var/log",
              "Use%": 0,
              "Available": 437.4,
              "Available.unit": "M",
              "Used": 572,
              "Used.unit": "K",
              "Size": 438,
              "Size.unit": "M",
              "Filesystem": "none"
            }
          }
        }
      }
    }

  ]
}